cogs/perm/__init__.py
d_snek_cogs_perm-0.0.3.dist-info/METADATA
d_snek_cogs_perm-0.0.3.dist-info/WHEEL
d_snek_cogs_perm-0.0.3.dist-info/top_level.txt
d_snek_cogs_perm-0.0.3.dist-info/RECORD
