Metadata-Version: 2.1
Name: d-snek-cogs-perm
Version: 0.0.3
Summary: Discord SNEK Cog; Perm
Home-page: https://git.jboi.dev/ShadowJonathan/snek-perm
Author: Jonathan de Jong
Author-email: jonathan@automatia.nl
License: UNKNOWN
Platform: UNKNOWN
Classifier: Programming Language :: Python :: 3
Classifier: License :: OSI Approved :: MIT License
Classifier: Operating System :: OS Independent
Requires-Python: >=3.6
Requires-Dist: d-snek (>=1.2.6)
Requires-Dist: discord.py (>=1.2.5)
Requires-Dist: ruamel.yaml
Provides-Extra: dev
Requires-Dist: ipython ; extra == 'dev'
Requires-Dist: twine ; extra == 'dev'
Requires-Dist: bump2version ; extra == 'dev'
